easy_scrape/__init__.py
easy_scrape/body_data.py
easy_scrape/scrape_table.py
easy_scrape-0.0.2.dist-info/METADATA
easy_scrape-0.0.2.dist-info/RECORD
easy_scrape-0.0.2.dist-info/WHEEL
easy_scrape-0.0.2.dist-info/top_level.txt
