Metadata-Version: 2.1
Name: easy-scrape
Version: 0.0.2
Summary: Helps in Scraping the Web
Home-page: https://github.com/sarthaknegi/easy_scrape
Author: Sarthak Negi
Author-email: sarthaknegi609@gmail.com
License: UNKNOWN
Platform: UNKNOWN
Classifier: Development Status :: 3 - Alpha
Classifier: Programming Language :: Python :: 3.6
Classifier: License :: OSI Approved :: MIT License
Classifier: Operating System :: OS Independent
